LootBotApi/LootBotApi.py
LootBotApi/__init__.py
LootBotApi/craft_needed.json
LootBotApi-0.5.9.3.dist-info/METADATA
LootBotApi-0.5.9.3.dist-info/WHEEL
LootBotApi-0.5.9.3.dist-info/top_level.txt
LootBotApi-0.5.9.3.dist-info/RECORD
