Metadata-Version: 2.1
Name: LootBotApi
Version: 0.5.9.3
Summary: API wrapper for Loot Bot
Home-page: https://github.com/Anatras02/LootBotApi
Author: Anatras02
Author-email: balderialessio@gmail.com
License: MIT
Platform: UNKNOWN
Classifier: License :: OSI Approved :: MIT License
Classifier: Programming Language :: Python :: 3
Classifier: Programming Language :: Python :: 3.7
Requires-Dist: requests
Requires-Dist: munch
